spiderfoot_neo4j/db.py
spiderfoot_neo4j/sfgraph.py
spiderfoot_neo4j-1.0.1.dist-info/entry_points.txt
spiderfoot_neo4j-1.0.1.dist-info/LICENSE
spiderfoot_neo4j-1.0.1.dist-info/WHEEL
spiderfoot_neo4j-1.0.1.dist-info/METADATA
spiderfoot_neo4j-1.0.1.dist-info/RECORD
